rabbit_connection/__init__.py
rabbit_connection/connection/__init__.py
rabbit_connection/connection/base_connection.py
rabbit_connection/consumer/__init__.py
rabbit_connection/consumer/base_consumer.py
rabbit_connection/publisher/__init__.py
rabbit_connection/publisher/base_publisher.py
pwx_rabbitmq_connection-1.0.4.dist-info/METADATA
pwx_rabbitmq_connection-1.0.4.dist-info/WHEEL
pwx_rabbitmq_connection-1.0.4.dist-info/top_level.txt
pwx_rabbitmq_connection-1.0.4.dist-info/RECORD
