Metadata-Version: 2.1
Name: pwx-rabbitmq-connection
Version: 1.0.4
Summary: Connection to RabbitMQ - PWX
Home-page: UNKNOWN
Author: Guilherme Rosa Koerich
Author-email: guilherme@pwx.cloud
License: UNKNOWN
Keywords: connection rabbitmq pwx
Platform: UNKNOWN
Classifier: Programming Language :: Python :: 3
Classifier: Programming Language :: Python :: 3.7
Requires-Python: >3.4
Requires-Dist: pika (==1.1.0)
